pymarco/__init__.py
pymarco/data/__init__.py
pymarco/data/countries.py
pymarco/data/currencies.py
pymarco/data/languages.py
pymarco/main.py
pymarco/models.py
pymarco-0.1.0.dist-info/LICENSE
pymarco-0.1.0.dist-info/METADATA
pymarco-0.1.0.dist-info/WHEEL
pymarco-0.1.0.dist-info/RECORD
