Metadata-Version: 2.1
Name: pymarco
Version: 0.1.0
Summary: A short description of the project.
Author: walidsa3d
Requires-Python: >=3.10,<4.0
Classifier: Programming Language :: Python :: 3
Classifier: Programming Language :: Python :: 3.10
Classifier: Programming Language :: Python :: 3.11
Classifier: Programming Language :: Python :: 3.12
Classifier: Programming Language :: Python :: 3.13
